README.rst
setup.py
dumpenv/__init__.py
dumpenv.egg-info/PKG-INFO
dumpenv.egg-info/SOURCES.txt
dumpenv.egg-info/dependency_links.txt
dumpenv.egg-info/entry_points.txt
dumpenv.egg-info/requires.txt
dumpenv.egg-info/top_level.txt
dumpenv/tests/__init__.py
dumpenv/tests/test_dumpenv.py
dumpenv/tests/test_setup.py