Metadata-Version: 1.1
Name: dumpenv
Version: 2018.12.0
Summary: dumpenv: Dump values of the current Python environment
Home-page: https://github.com/guettli/dumpenv/
Author: Thomas Guettler
Author-email: info.dumpenv@thomas-guettler.de
License: Apache Software License 2.0
Platform: UNKNOWN
Classifier: Development Status :: 5 - Production/Stable
Classifier: Intended Audience :: Information Technology
Classifier: License :: OSI Approved :: Apache Software License
Classifier: Programming Language :: Python :: 2
Classifier: Programming Language :: Python :: 3
